{
   "android_play_store_link":"https://play.google.com/store/apps/details?id=com.antspace.stickers.sudamericano",
   "ios_app_store_link":"",
   "sticker_packs":[
      {
         "identifier":"bolivar2021",
         "name":"Bolivar 2021",
         "animated_sticker_pack":false,
         "stickers":"29"
      },
      {
         "identifier":"thestrongest2021",
         "name":"The Strongest",
         "animated_sticker_pack":false,
         "stickers":"30"
      },
      {
         "identifier":"bolivar2020",
         "name":"Bolivar 2020",
         "animated_sticker_pack":false,
         "stickers":"15"
      },
      {
         "identifier":"wilstermann2020",
         "name":"Wilstermann",
         "animated_sticker_pack":false,
         "stickers":"15"
      }
   ]
}